{
  "generated": "2026-07-11T23:22:50.953Z",
  "corpus": {
    "scope": "NT+LXX",
    "tokens": 617364,
    "verses": 31090
  },
  "coverage": [
    {
      "id": "prayer",
      "label": "祈り",
      "terms": 7,
      "occurrences": 430,
      "books": 48,
      "verses": 352
    },
    {
      "id": "love",
      "label": "愛",
      "terms": 4,
      "occurrences": 547,
      "books": 55,
      "verses": 469
    },
    {
      "id": "faith",
      "label": "信仰",
      "terms": 3,
      "occurrences": 677,
      "books": 48,
      "verses": 615
    },
    {
      "id": "salvation",
      "label": "救い",
      "terms": 4,
      "occurrences": 312,
      "books": 43,
      "verses": 298
    },
    {
      "id": "grace",
      "label": "恵み",
      "terms": 3,
      "occurrences": 273,
      "books": 38,
      "verses": 256
    },
    {
      "id": "righteousness",
      "label": "義",
      "terms": 4,
      "occurrences": 944,
      "books": 57,
      "verses": 856
    },
    {
      "id": "sin",
      "label": "罪",
      "terms": 4,
      "occurrences": 977,
      "books": 51,
      "verses": 837
    },
    {
      "id": "holy",
      "label": "聖",
      "terms": 5,
      "occurrences": 1128,
      "books": 58,
      "verses": 949
    },
    {
      "id": "kingdom",
      "label": "御国",
      "terms": 2,
      "occurrences": 816,
      "books": 46,
      "verses": 703
    },
    {
      "id": "glory",
      "label": "栄光",
      "terms": 3,
      "occurrences": 624,
      "books": 54,
      "verses": 570
    },
    {
      "id": "resurrection",
      "label": "復活",
      "terms": 4,
      "occurrences": 52,
      "books": 18,
      "verses": 50
    },
    {
      "id": "hope",
      "label": "希望",
      "terms": 3,
      "occurrences": 259,
      "books": 38,
      "verses": 245
    },
    {
      "id": "truth",
      "label": "真理",
      "terms": 4,
      "occurrences": 350,
      "books": 51,
      "verses": 323
    },
    {
      "id": "peace",
      "label": "平安",
      "terms": 5,
      "occurrences": 360,
      "books": 57,
      "verses": 327
    },
    {
      "id": "repentance",
      "label": "悔い改め",
      "terms": 3,
      "occurrences": 63,
      "books": 11,
      "verses": 58
    }
  ],
  "lemmaDetail": [
    {
      "concept": "prayer",
      "lemma": "προσεύχομαι",
      "occ": 85
    },
    {
      "concept": "prayer",
      "lemma": "προσευχή",
      "occ": 102
    },
    {
      "concept": "prayer",
      "lemma": "δέομαι",
      "occ": 26
    },
    {
      "concept": "prayer",
      "lemma": "δέησις",
      "occ": 74
    },
    {
      "concept": "prayer",
      "lemma": "εὐχή",
      "occ": 77
    },
    {
      "concept": "prayer",
      "lemma": "εὔχομαι",
      "occ": 64
    },
    {
      "concept": "prayer",
      "lemma": "ἔντευξις",
      "occ": 2
    },
    {
      "concept": "love",
      "lemma": "ἀγαπάω",
      "occ": 353
    },
    {
      "concept": "love",
      "lemma": "ἀγάπη",
      "occ": 131
    },
    {
      "concept": "love",
      "lemma": "φιλέω",
      "occ": 53
    },
    {
      "concept": "love",
      "lemma": "φιλία",
      "occ": 10
    },
    {
      "concept": "faith",
      "lemma": "πίστις",
      "occ": 275
    },
    {
      "concept": "faith",
      "lemma": "πιστεύω",
      "occ": 290
    },
    {
      "concept": "faith",
      "lemma": "πιστός",
      "occ": 112
    },
    {
      "concept": "salvation",
      "lemma": "σῴζω",
      "occ": 106
    },
    {
      "concept": "salvation",
      "lemma": "σωτηρία",
      "occ": 153
    },
    {
      "concept": "salvation",
      "lemma": "σωτήρ",
      "occ": 48
    },
    {
      "concept": "salvation",
      "lemma": "σωτήριος",
      "occ": 5
    },
    {
      "concept": "grace",
      "lemma": "χάρις",
      "occ": 232
    },
    {
      "concept": "grace",
      "lemma": "χαρίζομαι",
      "occ": 24
    },
    {
      "concept": "grace",
      "lemma": "χάρισμα",
      "occ": 17
    },
    {
      "concept": "righteousness",
      "lemma": "δικαιοσύνη",
      "occ": 352
    },
    {
      "concept": "righteousness",
      "lemma": "δίκαιος",
      "occ": 387
    },
    {
      "concept": "righteousness",
      "lemma": "δικαιόω",
      "occ": 69
    },
    {
      "concept": "righteousness",
      "lemma": "δικαίωμα",
      "occ": 136
    },
    {
      "concept": "sin",
      "lemma": "ἁμαρτία",
      "occ": 578
    },
    {
      "concept": "sin",
      "lemma": "ἁμαρτάνω",
      "occ": 239
    },
    {
      "concept": "sin",
      "lemma": "ἁμάρτημα",
      "occ": 24
    },
    {
      "concept": "sin",
      "lemma": "ἁμαρτωλός",
      "occ": 136
    },
    {
      "concept": "holy",
      "lemma": "ἅγιος",
      "occ": 866
    },
    {
      "concept": "holy",
      "lemma": "ἁγιάζω",
      "occ": 193
    },
    {
      "concept": "holy",
      "lemma": "ἁγιασμός",
      "occ": 12
    },
    {
      "concept": "holy",
      "lemma": "ἁγιωσύνη",
      "occ": 7
    },
    {
      "concept": "holy",
      "lemma": "ὅσιος",
      "occ": 50
    },
    {
      "concept": "kingdom",
      "lemma": "βασιλεία",
      "occ": 453
    },
    {
      "concept": "kingdom",
      "lemma": "βασιλεύω",
      "occ": 363
    },
    {
      "concept": "glory",
      "lemma": "δόξα",
      "occ": 445
    },
    {
      "concept": "glory",
      "lemma": "δοξάζω",
      "occ": 132
    },
    {
      "concept": "glory",
      "lemma": "ἔνδοξος",
      "occ": 47
    },
    {
      "concept": "resurrection",
      "lemma": "ἀνάστασις",
      "occ": 45
    },
    {
      "concept": "resurrection",
      "lemma": "ἔγερσις",
      "occ": 2
    },
    {
      "concept": "resurrection",
      "lemma": "ἐξανάστασις",
      "occ": 2
    },
    {
      "concept": "resurrection",
      "lemma": "συνεγείρω",
      "occ": 3
    },
    {
      "concept": "hope",
      "lemma": "ἐλπίς",
      "occ": 131
    },
    {
      "concept": "hope",
      "lemma": "ἐλπίζω",
      "occ": 127
    },
    {
      "concept": "hope",
      "lemma": "προελπίζω",
      "occ": 1
    },
    {
      "concept": "truth",
      "lemma": "ἀλήθεια",
      "occ": 240
    },
    {
      "concept": "truth",
      "lemma": "ἀληθής",
      "occ": 38
    },
    {
      "concept": "truth",
      "lemma": "ἀληθινός",
      "occ": 66
    },
    {
      "concept": "truth",
      "lemma": "ἀληθεύω",
      "occ": 6
    },
    {
      "concept": "peace",
      "lemma": "εἰρήνη",
      "occ": 306
    },
    {
      "concept": "peace",
      "lemma": "εἰρηνεύω",
      "occ": 13
    },
    {
      "concept": "peace",
      "lemma": "εἰρηνικός",
      "occ": 38
    },
    {
      "concept": "peace",
      "lemma": "εἰρηνοποιέω",
      "occ": 2
    },
    {
      "concept": "peace",
      "lemma": "εἰρηνοποιός",
      "occ": 1
    },
    {
      "concept": "repentance",
      "lemma": "μετάνοια",
      "occ": 23
    },
    {
      "concept": "repentance",
      "lemma": "μετανοέω",
      "occ": 34
    },
    {
      "concept": "repentance",
      "lemma": "μεταμέλομαι",
      "occ": 6
    }
  ],
  "balance": {
    "high": {
      "id": "holy",
      "label": "聖",
      "terms": 5,
      "occurrences": 1128,
      "books": 58,
      "verses": 949
    },
    "low": {
      "id": "resurrection",
      "label": "復活",
      "terms": 4,
      "occurrences": 52,
      "books": 18,
      "verses": 50
    },
    "ratio": 21.7
  },
  "candidates": {
    "glossClusters": [
      {
        "keyword": "主",
        "occurrences": 8226,
        "lemmaCount": 7,
        "sampleLemmas": [
          "κύριος",
          "κυριεύω",
          "παράκλητος",
          "χρεοφειλέτης",
          "κυριακός"
        ]
      },
      {
        "keyword": "子",
        "occurrences": 5362,
        "lemmaCount": 13,
        "sampleLemmas": [
          "υἱός",
          "τέκνον",
          "παιδίον",
          "ἔριφος",
          "πῶλος"
        ]
      },
      {
        "keyword": "行",
        "occurrences": 4748,
        "lemmaCount": 31,
        "sampleLemmas": [
          "ποιέω",
          "πορεύομαι",
          "ἀδικέω",
          "πράσσω",
          "κακοποιέω"
        ]
      },
      {
        "keyword": "神",
        "occurrences": 4505,
        "lemmaCount": 9,
        "sampleLemmas": [
          "θεός",
          "θεῖος",
          "θεοσεβής",
          "θεομάχος",
          "θεοστυγής"
        ]
      },
      {
        "keyword": "言",
        "occurrences": 4490,
        "lemmaCount": 18,
        "sampleLemmas": [
          "λέγω",
          "φημί",
          "ῥέω",
          "κωφός",
          "παράδοσις"
        ]
      },
      {
        "keyword": "人",
        "occurrences": 2974,
        "lemmaCount": 64,
        "sampleLemmas": [
          "ἄνθρωπος",
          "Ἰουδαῖος",
          "Λευίτης",
          "Αἰγύπτιος",
          "Φαρισαῖος"
        ]
      },
      {
        "keyword": "王",
        "occurrences": 2760,
        "lemmaCount": 3,
        "sampleLemmas": [
          "βασιλεύς",
          "βασιλικός",
          "βασίλειος"
        ]
      },
      {
        "keyword": "見",
        "occurrences": 2729,
        "lemmaCount": 17,
        "sampleLemmas": [
          "ὁράω",
          "εὑρίσκω",
          "βλέπω",
          "θεωρέω",
          "θεάομαι"
        ]
      },
      {
        "keyword": "日",
        "occurrences": 2442,
        "lemmaCount": 3,
        "sampleLemmas": [
          "ἡμέρα",
          "ἐπιούσιος",
          "ἐφήμερος"
        ]
      },
      {
        "keyword": "家",
        "occurrences": 2265,
        "lemmaCount": 7,
        "sampleLemmas": [
          "οἶκος",
          "οἰκία",
          "οἰκοδεσπότης",
          "ἐνδημέω",
          "οἰκιακός"
        ]
      },
      {
        "keyword": "与",
        "occurrences": 2144,
        "lemmaCount": 10,
        "sampleLemmas": [
          "δίδωμι",
          "ψωμίζω",
          "παρέχω",
          "μεταδίδωμι",
          "συγκοινωνός"
        ]
      },
      {
        "keyword": "受",
        "occurrences": 1869,
        "lemmaCount": 31,
        "sampleLemmas": [
          "λαμβάνω",
          "κληρονομέω",
          "δέχομαι",
          "παραλαμβάνω",
          "δεκτός"
        ]
      },
      {
        "keyword": "民",
        "occurrences": 1851,
        "lemmaCount": 2,
        "sampleLemmas": [
          "λαός",
          "λαός"
        ]
      },
      {
        "keyword": "手",
        "occurrences": 1811,
        "lemmaCount": 9,
        "sampleLemmas": [
          "χείρ",
          "χειροποίητος",
          "κατασείω",
          "ἀχειροποίητος",
          "λέντιον"
        ]
      },
      {
        "keyword": "来",
        "occurrences": 1795,
        "lemmaCount": 12,
        "sampleLemmas": [
          "ἔρχομαι",
          "ἥκω",
          "παραγίνομαι",
          "πάρειμι",
          "κομίζω"
        ]
      },
      {
        "keyword": "男",
        "occurrences": 1673,
        "lemmaCount": 3,
        "sampleLemmas": [
          "ἀνήρ",
          "ἄρσην",
          "ἀνδρίζομαι"
        ]
      },
      {
        "keyword": "父",
        "occurrences": 1528,
        "lemmaCount": 4,
        "sampleLemmas": [
          "πατήρ",
          "προπάτωρ",
          "πατρολῴας",
          "ἀπάτωρ"
        ]
      },
      {
        "keyword": "語",
        "occurrences": 1407,
        "lemmaCount": 13,
        "sampleLemmas": [
          "λαλέω",
          "διαλέγομαι",
          "παρρησιάζομαι",
          "ὁμιλέω",
          "ἐρεύγομαι"
        ]
      },
      {
        "keyword": "町",
        "occurrences": 1383,
        "lemmaCount": 2,
        "sampleLemmas": [
          "πόλις",
          "Πόλις"
        ]
      },
      {
        "keyword": "聞",
        "occurrences": 1368,
        "lemmaCount": 9,
        "sampleLemmas": [
          "ἀκούω",
          "ἀκοή",
          "εἰσακούω",
          "ἀκροατής",
          "παρακούω"
        ]
      },
      {
        "keyword": "一",
        "occurrences": 1202,
        "lemmaCount": 6,
        "sampleLemmas": [
          "εἷς",
          "ἀποδεκατόω",
          "δεκάτη",
          "δεκατόω",
          "στατήρ"
        ]
      },
      {
        "keyword": "顔",
        "occurrences": 1189,
        "lemmaCount": 3,
        "sampleLemmas": [
          "πρόσωπον",
          "ὄψις",
          "σκυθρωπός"
        ]
      },
      {
        "keyword": "名",
        "occurrences": 1112,
        "lemmaCount": 2,
        "sampleLemmas": [
          "ὄνομα",
          "τοὔνομα"
        ]
      },
      {
        "keyword": "女",
        "occurrences": 1039,
        "lemmaCount": 8,
        "sampleLemmas": [
          "γυνή",
          "θῆλυς",
          "γυναικεῖος",
          "γυνή",
          "μόδιος"
        ]
      },
      {
        "keyword": "生",
        "occurrences": 1016,
        "lemmaCount": 21,
        "sampleLemmas": [
          "ζάω",
          "γεννάω",
          "ζῷον",
          "φύω",
          "ζῳοποιέω"
        ]
      }
    ],
    "seedThemes": [
      {
        "keyword": "霊",
        "occurrences": 672,
        "lemmaCount": 2,
        "sampleLemmas": [
          "πνεῦμα",
          "πύθων"
        ],
        "registered": false
      },
      {
        "keyword": "命",
        "occurrences": 118,
        "lemmaCount": 11,
        "sampleLemmas": [
          "παραγγέλλω",
          "κελεύω",
          "διατάσσω",
          "ἐντέλλομαι",
          "ἐπιτάσσω"
        ],
        "registered": false
      },
      {
        "keyword": "死",
        "occurrences": 935,
        "lemmaCount": 14,
        "sampleLemmas": [
          "θάνατος",
          "νεκρός",
          "θανατόω",
          "ἀποθνῄσκω",
          "τελευτάω"
        ],
        "registered": false
      },
      {
        "keyword": "従順",
        "occurrences": 23,
        "lemmaCount": 3,
        "sampleLemmas": [
          "ὑπακοή",
          "ὑπήκοος",
          "εὐπειθής"
        ],
        "registered": false
      }
    ],
    "domains": [
      {
        "code": "92004",
        "occ": 26232,
        "label": "(ラベルなし)"
      },
      {
        "code": "89017",
        "occ": 4353,
        "label": "(ラベルなし)"
      },
      {
        "code": "93001",
        "occ": 3674,
        "label": "人名"
      },
      {
        "code": "33006",
        "occ": 3239,
        "label": "言う・述べる"
      },
      {
        "code": "12001",
        "occ": 3002,
        "label": "悪霊・悪魔"
      },
      {
        "code": "89015",
        "occ": 2804,
        "label": "(ラベルなし)"
      },
      {
        "code": "92003",
        "occ": 2439,
        "label": "(ラベルなし)"
      },
      {
        "code": "13001",
        "occ": 2243,
        "label": "存在する・いる"
      },
      {
        "code": "69002",
        "occ": 1856,
        "label": "(ラベルなし)"
      },
      {
        "code": "92001",
        "occ": 1841,
        "label": "(ラベルなし)"
      },
      {
        "code": "89023",
        "occ": 1778,
        "label": "(ラベルなし)"
      },
      {
        "code": "89007",
        "occ": 1574,
        "label": "属格関係（の・属する）"
      },
      {
        "code": "92007",
        "occ": 1401,
        "label": "(ラベルなし)"
      },
      {
        "code": "67002",
        "occ": 1314,
        "label": "時点・時刻"
      },
      {
        "code": "59003",
        "occ": 1289,
        "label": "(ラベルなし)"
      }
    ],
    "topLemmas": [
      {
        "lemma": "κύριος",
        "occ": 8171,
        "gloss": "主"
      },
      {
        "lemma": "εἰμί",
        "occ": 7824,
        "gloss": "〜である"
      },
      {
        "lemma": "πᾶς",
        "occ": 6495,
        "gloss": "すべての"
      },
      {
        "lemma": "υἱός",
        "occ": 4861,
        "gloss": "子"
      },
      {
        "lemma": "θεός",
        "occ": 4480,
        "gloss": "神"
      },
      {
        "lemma": "λέγω",
        "occ": 4258,
        "gloss": "言う"
      },
      {
        "lemma": "εἶπον",
        "occ": 3813,
        "gloss": ""
      },
      {
        "lemma": "ποιέω",
        "occ": 3285,
        "gloss": "行う"
      },
      {
        "lemma": "γῆ",
        "occ": 2971,
        "gloss": "地"
      },
      {
        "lemma": "βασιλεύς",
        "occ": 2741,
        "gloss": "王"
      },
      {
        "lemma": "Ἰσραήλ",
        "occ": 2542,
        "gloss": "イスラエル"
      },
      {
        "lemma": "ἡμέρα",
        "occ": 2439,
        "gloss": "日"
      },
      {
        "lemma": "δίδωμι",
        "occ": 2091,
        "gloss": "与える"
      },
      {
        "lemma": "οἶκος",
        "occ": 1934,
        "gloss": "家"
      },
      {
        "lemma": "λαός",
        "occ": 1850,
        "gloss": "民"
      },
      {
        "lemma": "χείρ",
        "occ": 1781,
        "gloss": "手"
      },
      {
        "lemma": "γίγνομαι",
        "occ": 1716,
        "gloss": ""
      },
      {
        "lemma": "ὁράω",
        "occ": 1672,
        "gloss": "見る"
      },
      {
        "lemma": "ἄνθρωπος",
        "occ": 1643,
        "gloss": "人"
      },
      {
        "lemma": "ἀνήρ",
        "occ": 1592,
        "gloss": "男"
      }
    ]
  },
  "fails": [],
  "warnings": [
    "[lemma] prayer: ἔντευξις の出現はわずか 2 回（孤立 lemma）",
    "[lemma] resurrection: ἔγερσις の出現はわずか 2 回（孤立 lemma）",
    "[lemma] resurrection: ἐξανάστασις の出現はわずか 2 回（孤立 lemma）",
    "[lemma] resurrection: συνεγείρω の出現はわずか 3 回（孤立 lemma）",
    "[lemma] hope: προελπίζω の出現はわずか 1 回（孤立 lemma）",
    "[lemma] peace: εἰρηνοποιέω の出現はわずか 2 回（孤立 lemma）",
    "[lemma] peace: εἰρηνοποιός の出現はわずか 1 回（孤立 lemma）",
    "[balance] 出現数の偏りが 21.7倍: High holy 1128 / Low resurrection 52"
  ]
}
